{"char_titles":[{"char":"arya","title":"princess"},{"char":"bryndenRivers","title":"ser"},{"char":"bryndenRivers","title":"handOfTheKing"},{"char":"bryndenRivers","title":"lordCommander"},{"char":"bryndenRivers","title":"masterWhisperers"},{"char":"catelynStark","title":"ladyOfWinterfell"},{"char":"gared","title":"ranger"},{"char":"ilynPayne","title":"ser"},{"char":"ilynPayne","title":"kingsJustice"},{"char":"ilynPayne","title":"captainOfGuards"},{"char":"jaimeLannister","title":"lordCommanderOfTheKingsguard"},{"char":"jaimeLannister","title":"ser"},{"char":"jaimeLannister","title":"wardenEast"},{"char":"jonSnow","title":"kingInTheNorth"},{"char":"jonSnow","title":"lordCommander"},{"char":"jonSnow","title":"steward"},{"char":"ned","title":"handOfTheKing"},{"char":"ned","title":"lordOfWinterfell"},{"char":"ned","title":"regent"},{"char":"ned","title":"wardenNorth"},{"char":"ned","title":"protectorOfRealm"},{"char":"olennaTyrell","title":"ladyOfHighgarden"},{"char":"olly","title":"steward"},{"char":"ramsay ","title":"lordOfWinterfell"},{"char":"ramsay ","title":"lordOfDreadfort"},{"char":"ramsay ","title":"lordOfHornwood"},{"char":"ramsay ","title":"wardenNorth"},{"char":"ramsay ","title":"lordParamountOfTheNorth"},{"char":"ramsay ","title":"castellanOfTheDreadfort"},{"char":"robertBaratheon","title":"kingOfTheAndals"},{"char":"robertBaratheon","title":"lordOfTheSevenKingdoms"},{"char":"robertBaratheon","title":"lordOfStormsEnd"},{"char":"robertBaratheon","title":"lordParamountOfTheStormlands"},{"char":"robertBaratheon","title":"protectorOfRealm"},{"char":"sansa","title":"princess"},{"char":"sansa","title":"ladyOfWinterfell"},{"char":"tyrion","title":"handOfTheKing"},{"char":"tyrion","title":"handOfTheQueen"},{"char":"tyrion","title":"masterCoin"},{"char":"waymarroyce","title":"ser"},{"char":"waymarroyce","title":"ranger"},{"char":"will","title":"ranger"}]}